{"data":[{"alignmentgroup":"True","hovertemplate":"Source=Coal<br>State=%{x}<br>Quadrillion BTU=%{y}<extra></extra>","legendgroup":"Coal","marker":{"color":"#525B76"},"name":"Coal","offsetgroup":"Coal","orientation":"v","showlegend":true,"textposition":"auto","type":"bar","x":["Alaska","Alabama","Arkansas","Arizona","California","Colorado","Connecticut","District of Columbia","Delaware","Florida","Georgia","Hawaii","Iowa","Idaho","Illinois","Indiana","Kansas","Kentucky","Louisiana","Massachussetts","Maryland","Maine","Michigan","Minnesota","Missouri","Mississippi","Montana","North Carolina","North Dakota","Nebraska","New Hampshire","New Jersey","New Mexico","Nevada","New York","Ohio","Oklahoma","Oregon","Pennsylvania","Rhode Island","South Carolina","South Dakota","Tennessee","Texas","Utah","Virginia","Vermont","Washington","Wisconsin","West Virginia","Wyoming"],"xaxis":"x","y":[0.013662,0.888436,0.275037,0.438524,0.066495,0.388586,0.039931,0.000502,0.063839,0.720824,0.934773,0.017107,0.465167,0.010261,1.091382,1.572084,0.396333,1.020709,0.2498,0.120168,0.327979,0.006583,0.801178,0.366208,0.802879,0.185063,0.20248,0.827974,0.420719,0.216872,0.044899,0.111799,0.296067,0.082871,0.25845,1.463773,0.373217,0.045461,1.491907,3.9e-05,0.444046,0.033256,0.672766,1.609155,0.391386,0.4582,3.4e-05,0.095737,0.465083,0.983259,0.494955],"yaxis":"y"},{"alignmentgroup":"True","hovertemplate":"Source=Natural gas<br>State=%{x}<br>Quadrillion BTU=%{y}<extra></extra>","legendgroup":"Natural gas","marker":{"color":"#EE7674"},"name":"Natural gas","offsetgroup":"Natural gas","orientation":"v","showlegend":true,"textposition":"auto","type":"bar","x":["Alaska","Alabama","Arkansas","Arizona","California","Colorado","Connecticut","District of Columbia","Delaware","Florida","Georgia","Hawaii","Iowa","Idaho","Illinois","Indiana","Kansas","Kentucky","Louisiana","Massachussetts","Maryland","Maine","Michigan","Minnesota","Missouri","Mississippi","Montana","North Carolina","North Dakota","Nebraska","New Hampshire","New Jersey","New Mexico","Nevada","New York","Ohio","Oklahoma","Oregon","Pennsylvania","Rhode Island","South Carolina","South Dakota","Tennessee","Texas","Utah","Virginia","Vermont","Washington","Wisconsin","West Virginia","Wyoming"],"xaxis":"x","y":[0.372186,0.430649,0.22961,0.401992,2.467545,0.512841,0.183604,0.033856,0.049932,0.943845,0.45522,0.000173,0.264166,0.083904,0.968652,0.5438,0.291695,0.235876,1.430621,0.418907,0.208439,0.067227,0.814887,0.395658,0.277919,0.37499,0.075077,0.244475,0.056842,0.15349,0.064856,0.640236,0.239858,0.262547,1.214349,0.835555,0.677472,0.26024,0.78009,0.090259,0.182201,0.054099,0.22952,3.626526,0.231125,0.331018,0.008874,0.279429,0.403947,0.124555,0.145985],"yaxis":"y"},{"alignmentgroup":"True","hovertemplate":"Source=Nuclear<br>State=%{x}<br>Quadrillion BTU=%{y}<extra></extra>","legendgroup":"Nuclear","marker":{"color":"#F4A259"},"name":"Nuclear","offsetgroup":"Nuclear","orientation":"v","showlegend":true,"textposition":"auto","type":"bar","x":["Alaska","Alabama","Arkansas","Arizona","California","Colorado","Connecticut","District of Columbia","Delaware","Florida","Georgia","Hawaii","Iowa","Idaho","Illinois","Indiana","Kansas","Kentucky","Louisiana","Massachussetts","Maryland","Maine","Michigan","Minnesota","Missouri","Mississippi","Montana","North Carolina","North Dakota","Nebraska","New Hampshire","New Jersey","New Mexico","Nevada","New York","Ohio","Oklahoma","Oregon","Pennsylvania","Rhode Island","South Carolina","South Dakota","Tennessee","Texas","Utah","Virginia","Vermont","Washington","Wisconsin","West Virginia","Wyoming"],"xaxis":"x","y":[0.0,0.360036,0.162434,0.28092,0.375427,0.0,0.171874,0.0,0.0,0.307215,0.341364,0.0,0.047398,0.0,1.0041,0.0,0.108762,0.0,0.179127,0.053701,0.150551,0.0,0.330581,0.137437,0.098302,0.098164,0.0,0.420029,0.0,0.115815,0.112902,0.335757,0.0,0.0,0.445288,0.165349,0.0,0.0,0.8116,0.0,0.558014,0.0,0.301038,0.429577,0.0,0.286019,0.049337,0.085051,0.135416,0.0,0.0],"yaxis":"y"},{"alignmentgroup":"True","hovertemplate":"Source=Petroleum<br>State=%{x}<br>Quadrillion BTU=%{y}<extra></extra>","legendgroup":"Petroleum","marker":{"color":"#7A89C2"},"name":"Petroleum","offsetgroup":"Petroleum","orientation":"v","showlegend":true,"textposition":"auto","type":"bar","x":["Alaska","Alabama","Arkansas","Arizona","California","Colorado","Connecticut","District of Columbia","Delaware","Florida","Georgia","Hawaii","Iowa","Idaho","Illinois","Indiana","Kansas","Kentucky","Louisiana","Massachussetts","Maryland","Maine","Michigan","Minnesota","Missouri","Mississippi","Montana","North Carolina","North Dakota","Nebraska","New Hampshire","New Jersey","New Mexico","Nevada","New York","Ohio","Oklahoma","Oregon","Pennsylvania","Rhode Island","South Carolina","South Dakota","Tennessee","Texas","Utah","Virginia","Vermont","Washington","Wisconsin","West Virginia","Wyoming"],"xaxis":"x","y":[0.323089,0.601179,0.359757,0.571417,3.795097,0.513431,0.377002,0.021547,0.11981,1.938437,1.052558,0.30354,0.420924,0.162468,1.324077,0.834645,0.402282,0.690076,2.130984,0.647827,0.531469,0.233431,0.919768,0.678958,0.730638,0.460954,0.206442,0.920732,0.139972,0.229195,0.16502,1.241757,0.277635,0.285879,1.562784,1.284301,0.563473,0.374647,1.402752,0.087046,0.533797,0.117482,0.773597,5.91714,0.299418,0.958752,0.086757,0.820408,0.58463,0.235366,0.16943],"yaxis":"y"},{"alignmentgroup":"True","hovertemplate":"Source=Renewables<br>State=%{x}<br>Quadrillion BTU=%{y}<extra></extra>","legendgroup":"Renewables","marker":{"color":"#9DBF9E"},"name":"Renewables","offsetgroup":"Renewables","orientation":"v","showlegend":true,"textposition":"auto","type":"bar","x":["Alaska","Alabama","Arkansas","Arizona","California","Colorado","Connecticut","District of Columbia","Delaware","Florida","Georgia","Hawaii","Iowa","Idaho","Illinois","Indiana","Kansas","Kentucky","Louisiana","Massachussetts","Maryland","Maine","Michigan","Minnesota","Missouri","Mississippi","Montana","North Carolina","North Dakota","Nebraska","New Hampshire","New Jersey","New Mexico","Nevada","New York","Ohio","Oklahoma","Oregon","Pennsylvania","Rhode Island","South Carolina","South Dakota","Tennessee","Texas","Utah","Virginia","Vermont","Washington","Wisconsin","West Virginia","Wyoming"],"xaxis":"x","y":[0.014286,0.229491,0.121766,0.097682,0.707689,0.050617,0.036173,0.000742,0.004974,0.199922,0.205849,0.017002,0.176851,0.127411,0.130915,0.067602,0.036181,0.06582,0.151977,0.05962,0.058135,0.156513,0.140683,0.15323,0.062175,0.06457,0.119592,0.117419,0.032353,0.064219,0.038434,0.052998,0.032004,0.042155,0.392388,0.084298,0.082596,0.402134,0.121913,0.006399,0.097885,0.069575,0.126961,0.250484,0.01423,0.135794,0.019025,0.89449,0.142051,0.026873,0.018963],"yaxis":"y"}],"layout":{"barmode":"relative","legend":{"title":{"text":"Source"},"tracegroupgap":0},"margin":{"t":60},"paper_bgcolor":"#fffffa","plot_bgcolor":"#fffffa","showlegend":false,"template":{"data":{"bar":[{"error_x":{"color":"#2a3f5f"},"error_y":{"color":"#2a3f5f"},"marker":{"line":{"color":"#E5ECF6","width":0.5}},"type":"bar"}],"barpolar":[{"marker":{"line":{"color":"#E5ECF6","width":0.5}},"type":"barpolar"}],"carpet":[{"aaxis":{"endlinecolor":"#2a3f5f","gridcolor":"white","linecolor":"white","minorgridcolor":"white","startlinecolor":"#2a3f5f"},"baxis":{"endlinecolor":"#2a3f5f","gridcolor":"white","linecolor":"white","minorgridcolor":"white","startlinecolor":"#2a3f5f"},"type":"carpet"}],"choropleth":[{"colorbar":{"outlinewidth":0,"ticks":""},"type":"choropleth"}],"contour":[{"colorbar":{"outlinewidth":0,"ticks":""},"colorscale":[[0.0,"#0d0887"],[0.1111111111111111,"#46039f"],[0.2222222222222222,"#7201a8"],[0.3333333333333333,"#9c179e"],[0.4444444444444444,"#bd3786"],[0.5555555555555556,"#d8576b"],[0.6666666666666666,"#ed7953"],[0.7777777777777778,"#fb9f3a"],[0.8888888888888888,"#fdca26"],[1.0,"#f0f921"]],"type":"contour"}],"contourcarpet":[{"colorbar":{"outlinewidth":0,"ticks":""},"type":"contourcarpet"}],"heatmap":[{"colorbar":{"outlinewidth":0,"ticks":""},"colorscale":[[0.0,"#0d0887"],[0.1111111111111111,"#46039f"],[0.2222222222222222,"#7201a8"],[0.3333333333333333,"#9c179e"],[0.4444444444444444,"#bd3786"],[0.5555555555555556,"#d8576b"],[0.6666666666666666,"#ed7953"],[0.7777777777777778,"#fb9f3a"],[0.8888888888888888,"#fdca26"],[1.0,"#f0f921"]],"type":"heatmap"}],"heatmapgl":[{"colorbar":{"outlinewidth":0,"ticks":""},"colorscale":[[0.0,"#0d0887"],[0.1111111111111111,"#46039f"],[0.2222222222222222,"#7201a8"],[0.3333333333333333,"#9c179e"],[0.4444444444444444,"#bd3786"],[0.5555555555555556,"#d8576b"],[0.6666666666666666,"#ed7953"],[0.7777777777777778,"#fb9f3a"],[0.8888888888888888,"#fdca26"],[1.0,"#f0f921"]],"type":"heatmapgl"}],"histogram":[{"marker":{"colorbar":{"outlinewidth":0,"ticks":""}},"type":"histogram"}],"histogram2d":[{"colorbar":{"outlinewidth":0,"ticks":""},"colorscale":[[0.0,"#0d0887"],[0.1111111111111111,"#46039f"],[0.2222222222222222,"#7201a8"],[0.3333333333333333,"#9c179e"],[0.4444444444444444,"#bd3786"],[0.5555555555555556,"#d8576b"],[0.6666666666666666,"#ed7953"],[0.7777777777777778,"#fb9f3a"],[0.8888888888888888,"#fdca26"],[1.0,"#f0f921"]],"type":"histogram2d"}],"histogram2dcontour":[{"colorbar":{"outlinewidth":0,"ticks":""},"colorscale":[[0.0,"#0d0887"],[0.1111111111111111,"#46039f"],[0.2222222222222222,"#7201a8"],[0.3333333333333333,"#9c179e"],[0.4444444444444444,"#bd3786"],[0.5555555555555556,"#d8576b"],[0.6666666666666666,"#ed7953"],[0.7777777777777778,"#fb9f3a"],[0.8888888888888888,"#fdca26"],[1.0,"#f0f921"]],"type":"histogram2dcontour"}],"mesh3d":[{"colorbar":{"outlinewidth":0,"ticks":""},"type":"mesh3d"}],"parcoords":[{"line":{"colorbar":{"outlinewidth":0,"ticks":""}},"type":"parcoords"}],"pie":[{"automargin":true,"type":"pie"}],"scatter":[{"marker":{"colorbar":{"outlinewidth":0,"ticks":""}},"type":"scatter"}],"scatter3d":[{"line":{"colorbar":{"outlinewidth":0,"ticks":""}},"marker":{"colorbar":{"outlinewidth":0,"ticks":""}},"type":"scatter3d"}],"scattercarpet":[{"marker":{"colorbar":{"outlinewidth":0,"ticks":""}},"type":"scattercarpet"}],"scattergeo":[{"marker":{"colorbar":{"outlinewidth":0,"ticks":""}},"type":"scattergeo"}],"scattergl":[{"marker":{"colorbar":{"outlinewidth":0,"ticks":""}},"type":"scattergl"}],"scattermapbox":[{"marker":{"colorbar":{"outlinewidth":0,"ticks":""}},"type":"scattermapbox"}],"scatterpolar":[{"marker":{"colorbar":{"outlinewidth":0,"ticks":""}},"type":"scatterpolar"}],"scatterpolargl":[{"marker":{"colorbar":{"outlinewidth":0,"ticks":""}},"type":"scatterpolargl"}],"scatterternary":[{"marker":{"colorbar":{"outlinewidth":0,"ticks":""}},"type":"scatterternary"}],"surface":[{"colorbar":{"outlinewidth":0,"ticks":""},"colorscale":[[0.0,"#0d0887"],[0.1111111111111111,"#46039f"],[0.2222222222222222,"#7201a8"],[0.3333333333333333,"#9c179e"],[0.4444444444444444,"#bd3786"],[0.5555555555555556,"#d8576b"],[0.6666666666666666,"#ed7953"],[0.7777777777777778,"#fb9f3a"],[0.8888888888888888,"#fdca26"],[1.0,"#f0f921"]],"type":"surface"}],"table":[{"cells":{"fill":{"color":"#EBF0F8"},"line":{"color":"white"}},"header":{"fill":{"color":"#C8D4E3"},"line":{"color":"white"}},"type":"table"}]},"layout":{"annotationdefaults":{"arrowcolor":"#2a3f5f","arrowhead":0,"arrowwidth":1},"autotypenumbers":"strict","coloraxis":{"colorbar":{"outlinewidth":0,"ticks":""}},"colorscale":{"diverging":[[0,"#8e0152"],[0.1,"#c51b7d"],[0.2,"#de77ae"],[0.3,"#f1b6da"],[0.4,"#fde0ef"],[0.5,"#f7f7f7"],[0.6,"#e6f5d0"],[0.7,"#b8e186"],[0.8,"#7fbc41"],[0.9,"#4d9221"],[1,"#276419"]],"sequential":[[0.0,"#0d0887"],[0.1111111111111111,"#46039f"],[0.2222222222222222,"#7201a8"],[0.3333333333333333,"#9c179e"],[0.4444444444444444,"#bd3786"],[0.5555555555555556,"#d8576b"],[0.6666666666666666,"#ed7953"],[0.7777777777777778,"#fb9f3a"],[0.8888888888888888,"#fdca26"],[1.0,"#f0f921"]],"sequentialminus":[[0.0,"#0d0887"],[0.1111111111111111,"#46039f"],[0.2222222222222222,"#7201a8"],[0.3333333333333333,"#9c179e"],[0.4444444444444444,"#bd3786"],[0.5555555555555556,"#d8576b"],[0.6666666666666666,"#ed7953"],[0.7777777777777778,"#fb9f3a"],[0.8888888888888888,"#fdca26"],[1.0,"#f0f921"]]},"colorway":["#636efa","#EF553B","#00cc96","#ab63fa","#FFA15A","#19d3f3","#FF6692","#B6E880","#FF97FF","#FECB52"],"font":{"color":"#2a3f5f"},"geo":{"bgcolor":"white","lakecolor":"white","landcolor":"#E5ECF6","showlakes":true,"showland":true,"subunitcolor":"white"},"hoverlabel":{"align":"left"},"hovermode":"closest","mapbox":{"style":"light"},"paper_bgcolor":"white","plot_bgcolor":"#E5ECF6","polar":{"angularaxis":{"gridcolor":"white","linecolor":"white","ticks":""},"bgcolor":"#E5ECF6","radialaxis":{"gridcolor":"white","linecolor":"white","ticks":""}},"scene":{"xaxis":{"backgroundcolor":"#E5ECF6","gridcolor":"white","gridwidth":2,"linecolor":"white","showbackground":true,"ticks":"","zerolinecolor":"white"},"yaxis":{"backgroundcolor":"#E5ECF6","gridcolor":"white","gridwidth":2,"linecolor":"white","showbackground":true,"ticks":"","zerolinecolor":"white"},"zaxis":{"backgroundcolor":"#E5ECF6","gridcolor":"white","gridwidth":2,"linecolor":"white","showbackground":true,"ticks":"","zerolinecolor":"white"}},"shapedefaults":{"line":{"color":"#2a3f5f"}},"ternary":{"aaxis":{"gridcolor":"white","linecolor":"white","ticks":""},"baxis":{"gridcolor":"white","linecolor":"white","ticks":""},"bgcolor":"#E5ECF6","caxis":{"gridcolor":"white","linecolor":"white","ticks":""}},"title":{"x":0.05},"xaxis":{"automargin":true,"gridcolor":"white","linecolor":"white","ticks":"","title":{"standoff":15},"zerolinecolor":"white","zerolinewidth":2},"yaxis":{"automargin":true,"gridcolor":"white","linecolor":"white","ticks":"","title":{"standoff":15},"zerolinecolor":"white","zerolinewidth":2}}},"xaxis":{"anchor":"y","categoryorder":"total ascending","domain":[0.0,1.0],"tickfont":{"size":8},"tickmode":"linear","title":{"text":""}},"yaxis":{"anchor":"x","domain":[0.0,1.0],"range":[0,14.90143515],"title":{"text":"Quadrillion BTU"}}}}